{
  "Finland": {
    "node_id": "Finland",
    "node_type": "jurisdiction",
    "label": "Finland",
    "region": "Global North",
    "in_degree": 1,
    "out_degree": 17,
    "total_degree": 18,
    "lat": 61.9241,
    "lon": 25.7482
  },
  "European Court of Human Rights (International)": {
    "node_id": "European Court of Human Rights (International)",
    "node_type": "jurisdiction",
    "label": "European Court of Human Rights (International)",
    "region": "International",
    "in_degree": 263,
    "out_degree": 0,
    "total_degree": 263,
    "lat": null,
    "lon": null
  },
  "International - Council of Europe": {
    "node_id": "International - Council of Europe",
    "node_type": "jurisdiction",
    "label": "International - Council of Europe",
    "region": "International",
    "in_degree": 1,
    "out_degree": 0,
    "total_degree": 1,
    "lat": null,
    "lon": null
  },
  "International (United States as arbitrator)": {
    "node_id": "International (United States as arbitrator)",
    "node_type": "jurisdiction",
    "label": "International (United States as arbitrator)",
    "region": "International",
    "in_degree": 2,
    "out_degree": 0,
    "total_degree": 2,
    "lat": null,
    "lon": null
  },
  "International (NAFTA/ICSID)": {
    "node_id": "International (NAFTA/ICSID)",
    "node_type": "jurisdiction",
    "label": "International (NAFTA/ICSID)",
    "region": "International",
    "in_degree": 1,
    "out_degree": 0,
    "total_degree": 1,
    "lat": null,
    "lon": null
  },
  "Saint Lucia": {
    "node_id": "Saint Lucia",
    "node_type": "jurisdiction",
    "label": "Saint Lucia",
    "region": "Global South",
    "in_degree": 2,
    "out_degree": 0,
    "total_degree": 2,
    "lat": null,
    "lon": null
  },
  "Not a legal case": {
    "node_id": "Not a legal case",
    "node_type": "jurisdiction",
    "label": "Not a legal case",
    "region": "Not applicable",
    "in_degree": 3,
    "out_degree": 0,
    "total_degree": 3,
    "lat": null,
    "lon": null
  },
  "International (WTO)": {
    "node_id": "International (WTO)",
    "node_type": "jurisdiction",
    "label": "International (WTO)",
    "region": "International",
    "in_degree": 98,
    "out_degree": 0,
    "total_degree": 98,
    "lat": 46.2206,
    "lon": 6.143
  },
  "Namibia": {
    "node_id": "Namibia",
    "node_type": "jurisdiction",
    "label": "Namibia",
    "region": "Global South",
    "in_degree": 1,
    "out_degree": 4,
    "total_degree": 5,
    "lat": null,
    "lon": null
  },
  "Council of Europe (International Court)": {
    "node_id": "Council of Europe (International Court)",
    "node_type": "jurisdiction",
    "label": "Council of Europe (International Court)",
    "region": "International",
    "in_degree": 1,
    "out_degree": 0,
    "total_degree": 1,
    "lat": null,
    "lon": null
  },
  "East Africa (Kenya, Tanzania, or Uganda)": {
    "node_id": "East Africa (Kenya, Tanzania, or Uganda)",
    "node_type": "jurisdiction",
    "label": "East Africa (Kenya, Tanzania, or Uganda)",
    "region": "Global South",
    "in_degree": 1,
    "out_degree": 0,
    "total_degree": 1,
    "lat": null,
    "lon": null
  },
  "Philippines": {
    "node_id": "Philippines",
    "node_type": "jurisdiction",
    "label": "Philippines",
    "region": "Global South",
    "in_degree": 20,
    "out_degree": 31,
    "total_degree": 51,
    "lat": 12.8797,
    "lon": 121.774
  },
  "International (Inter-American Court of Human Rights)": {
    "node_id": "International (Inter-American Court of Human Rights)",
    "node_type": "jurisdiction",
    "label": "International (Inter-American Court of Human Rights)",
    "region": "International",
    "in_degree": 164,
    "out_degree": 0,
    "total_degree": 164,
    "lat": 9.9281,
    "lon": -84.0907
  },
  "France (European Court of Human Rights)": {
    "node_id": "France (European Court of Human Rights)",
    "node_type": "jurisdiction",
    "label": "France (European Court of Human Rights)",
    "region": "International",
    "in_degree": 1,
    "out_degree": 0,
    "total_degree": 1,
    "lat": null,
    "lon": null
  },
  "International (United Nations)": {
    "node_id": "International (United Nations)",
    "node_type": "jurisdiction",
    "label": "International (United Nations)",
    "region": "International",
    "in_degree": 13,
    "out_degree": 0,
    "total_degree": 13,
    "lat": null,
    "lon": null
  },
  "Netherlands": {
    "node_id": "Netherlands",
    "node_type": "jurisdiction",
    "label": "Netherlands",
    "region": "Global North",
    "in_degree": 168,
    "out_degree": 133,
    "total_degree": 301,
    "lat": 52.1326,
    "lon": 5.2913
  },
  "Switzerland": {
    "node_id": "Switzerland",
    "node_type": "jurisdiction",
    "label": "Switzerland",
    "region": "International",
    "in_degree": 50,
    "out_degree": 215,
    "total_degree": 265,
    "lat": 46.8182,
    "lon": 8.2275
  },
  "France (case before European Court of Human Rights)": {
    "node_id": "France (case before European Court of Human Rights)",
    "node_type": "jurisdiction",
    "label": "France (case before European Court of Human Rights)",
    "region": "International",
    "in_degree": 2,
    "out_degree": 0,
    "total_degree": 2,
    "lat": null,
    "lon": null
  },
  "International/European": {
    "node_id": "International/European",
    "node_type": "jurisdiction",
    "label": "International/European",
    "region": "International",
    "in_degree": 2,
    "out_degree": 0,
    "total_degree": 2,
    "lat": null,
    "lon": null
  },
  "Canada": {
    "node_id": "Canada",
    "node_type": "jurisdiction",
    "label": "Canada",
    "region": "Global North",
    "in_degree": 53,
    "out_degree": 127,
    "total_degree": 180,
    "lat": 56.1304,
    "lon": -106.3468
  },
  "United States": {
    "node_id": "United States",
    "node_type": "jurisdiction",
    "label": "United States",
    "region": "Global North",
    "in_degree": 167,
    "out_degree": 1,
    "total_degree": 168,
    "lat": 37.0902,
    "lon": -95.7129
  },
  "Argentina": {
    "node_id": "Argentina",
    "node_type": "jurisdiction",
    "label": "Argentina",
    "region": "International",
    "in_degree": 16,
    "out_degree": 41,
    "total_degree": 57,
    "lat": -38.4161,
    "lon": -63.6167
  },
  "Switzerland (European Court of Human Rights)": {
    "node_id": "Switzerland (European Court of Human Rights)",
    "node_type": "jurisdiction",
    "label": "Switzerland (European Court of Human Rights)",
    "region": "International",
    "in_degree": 1,
    "out_degree": 0,
    "total_degree": 1,
    "lat": null,
    "lon": null
  },
  "Grenada": {
    "node_id": "Grenada",
    "node_type": "jurisdiction",
    "label": "Grenada",
    "region": "Global South",
    "in_degree": 0,
    "out_degree": 17,
    "total_degree": 17,
    "lat": null,
    "lon": null
  },
  "Scotland, United Kingdom": {
    "node_id": "Scotland, United Kingdom",
    "node_type": "jurisdiction",
    "label": "Scotland, United Kingdom",
    "region": "Global North",
    "in_degree": 5,
    "out_degree": 0,
    "total_degree": 5,
    "lat": null,
    "lon": null
  },
  "France/European Union": {
    "node_id": "France/European Union",
    "node_type": "jurisdiction",
    "label": "France/European Union",
    "region": "International",
    "in_degree": 2,
    "out_degree": 0,
    "total_degree": 2,
    "lat": null,
    "lon": null
  },
  "United Kingdom (Scotland)": {
    "node_id": "United Kingdom (Scotland)",
    "node_type": "jurisdiction",
    "label": "United Kingdom (Scotland)",
    "region": "Global North",
    "in_degree": 7,
    "out_degree": 0,
    "total_degree": 7,
    "lat": null,
    "lon": null
  },
  "Panama": {
    "node_id": "Panama",
    "node_type": "jurisdiction",
    "label": "Panama",
    "region": "Global South",
    "in_degree": 1,
    "out_degree": 0,
    "total_degree": 1,
    "lat": null,
    "lon": null
  },
  "Pakistan": {
    "node_id": "Pakistan",
    "node_type": "jurisdiction",
    "label": "Pakistan",
    "region": "Global South",
    "in_degree": 12,
    "out_degree": 15,
    "total_degree": 27,
    "lat": 30.3753,
    "lon": 69.3451
  },
  "Belgium": {
    "node_id": "Belgium",
    "node_type": "jurisdiction",
    "label": "Belgium",
    "region": "International",
    "in_degree": 28,
    "out_degree": 150,
    "total_degree": 178,
    "lat": 50.5039,
    "lon": 4.4699
  },
  "Norway": {
    "node_id": "Norway",
    "node_type": "jurisdiction",
    "label": "Norway",
    "region": "Global North",
    "in_degree": 18,
    "out_degree": 64,
    "total_degree": 82,
    "lat": 60.472,
    "lon": 8.4689
  },
  "Papua New Guinea": {
    "node_id": "Papua New Guinea",
    "node_type": "jurisdiction",
    "label": "Papua New Guinea",
    "region": "Global South",
    "in_degree": 1,
    "out_degree": 29,
    "total_degree": 30,
    "lat": null,
    "lon": null
  },
  "Hong Kong (Special Administrative Region of China)": {
    "node_id": "Hong Kong (Special Administrative Region of China)",
    "node_type": "jurisdiction",
    "label": "Hong Kong (Special Administrative Region of China)",
    "region": "Global North",
    "in_degree": 1,
    "out_degree": 0,
    "total_degree": 1,
    "lat": null,
    "lon": null
  },
  "Chile": {
    "node_id": "Chile",
    "node_type": "jurisdiction",
    "label": "Chile",
    "region": "Global South",
    "in_degree": 7,
    "out_degree": 3,
    "total_degree": 10,
    "lat": -35.6751,
    "lon": -71.543
  },
  "Trinidad and Tobago": {
    "node_id": "Trinidad and Tobago",
    "node_type": "jurisdiction",
    "label": "Trinidad and Tobago",
    "region": "Global South",
    "in_degree": 1,
    "out_degree": 0,
    "total_degree": 1,
    "lat": null,
    "lon": null
  },
  "Nigeria": {
    "node_id": "Nigeria",
    "node_type": "jurisdiction",
    "label": "Nigeria",
    "region": "Global South",
    "in_degree": 5,
    "out_degree": 39,
    "total_degree": 44,
    "lat": 9.082,
    "lon": 8.6753
  },
  "Greece": {
    "node_id": "Greece",
    "node_type": "jurisdiction",
    "label": "Greece",
    "region": "Global North",
    "in_degree": 2,
    "out_degree": 0,
    "total_degree": 2,
    "lat": null,
    "lon": null
  },
  "International (European Court of Human Rights)": {
    "node_id": "International (European Court of Human Rights)",
    "node_type": "jurisdiction",
    "label": "International (European Court of Human Rights)",
    "region": "International",
    "in_degree": 206,
    "out_degree": 0,
    "total_degree": 206,
    "lat": null,
    "lon": null
  },
  "International Arbitration": {
    "node_id": "International Arbitration",
    "node_type": "jurisdiction",
    "label": "International Arbitration",
    "region": "International",
    "in_degree": 153,
    "out_degree": 0,
    "total_degree": 153,
    "lat": null,
    "lon": null
  },
  "Czechia": {
    "node_id": "Czechia",
    "node_type": "jurisdiction",
    "label": "Czechia",
    "region": "Global South",
    "in_degree": 0,
    "out_degree": 144,
    "total_degree": 144,
    "lat": null,
    "lon": null
  },
  "Japan": {
    "node_id": "Japan",
    "node_type": "jurisdiction",
    "label": "Japan",
    "region": "Global North",
    "in_degree": 0,
    "out_degree": 3,
    "total_degree": 3,
    "lat": null,
    "lon": null
  },
  "Czech Republic": {
    "node_id": "Czech Republic",
    "node_type": "jurisdiction",
    "label": "Czech Republic",
    "region": "Global North",
    "in_degree": 52,
    "out_degree": 0,
    "total_degree": 52,
    "lat": null,
    "lon": null
  },
  "International (Sweden)": {
    "node_id": "International (Sweden)",
    "node_type": "jurisdiction",
    "label": "International (Sweden)",
    "region": "International",
    "in_degree": 2,
    "out_degree": 0,
    "total_degree": 2,
    "lat": null,
    "lon": null
  },
  "International/Regional (African Union)": {
    "node_id": "International/Regional (African Union)",
    "node_type": "jurisdiction",
    "label": "International/Regional (African Union)",
    "region": "International",
    "in_degree": 2,
    "out_degree": 0,
    "total_degree": 2,
    "lat": null,
    "lon": null
  },
  "European Union": {
    "node_id": "European Union",
    "node_type": "jurisdiction",
    "label": "European Union",
    "region": "International",
    "in_degree": 1424,
    "out_degree": 0,
    "total_degree": 1424,
    "lat": null,
    "lon": null
  },
  "Spain (International Court)": {
    "node_id": "Spain (International Court)",
    "node_type": "jurisdiction",
    "label": "Spain (International Court)",
    "region": "International",
    "in_degree": 2,
    "out_degree": 0,
    "total_degree": 2,
    "lat": null,
    "lon": null
  },
  "International (European Union)": {
    "node_id": "International (European Union)",
    "node_type": "jurisdiction",
    "label": "International (European Union)",
    "region": "International",
    "in_degree": 5,
    "out_degree": 0,
    "total_degree": 5,
    "lat": null,
    "lon": null
  },
  "Angola": {
    "node_id": "Angola",
    "node_type": "jurisdiction",
    "label": "Angola",
    "region": "Global South",
    "in_degree": 1,
    "out_degree": 0,
    "total_degree": 1,
    "lat": null,
    "lon": null
  },
  "European Court of Human Rights (International Court)": {
    "node_id": "European Court of Human Rights (International Court)",
    "node_type": "jurisdiction",
    "label": "European Court of Human Rights (International Court)",
    "region": "International",
    "in_degree": 3,
    "out_degree": 0,
    "total_degree": 3,
    "lat": 48.6,
    "lon": 7.75
  },
  "Ireland": {
    "node_id": "Ireland",
    "node_type": "jurisdiction",
    "label": "Ireland",
    "region": "Global North",
    "in_degree": 20,
    "out_degree": 133,
    "total_degree": 153,
    "lat": 53.1424,
    "lon": -7.6921
  },
  "Bermuda": {
    "node_id": "Bermuda",
    "node_type": "jurisdiction",
    "label": "Bermuda",
    "region": "Global North",
    "in_degree": 2,
    "out_degree": 0,
    "total_degree": 2,
    "lat": null,
    "lon": null
  },
  "European Union (Denmark)": {
    "node_id": "European Union (Denmark)",
    "node_type": "jurisdiction",
    "label": "European Union (Denmark)",
    "region": "International",
    "in_degree": 1,
    "out_degree": 0,
    "total_degree": 1,
    "lat": null,
    "lon": null
  },
  "European Union (European Court of Human Rights/European General Court)": {
    "node_id": "European Union (European Court of Human Rights/European General Court)",
    "node_type": "jurisdiction",
    "label": "European Union (European Court of Human Rights/European General Court)",
    "region": "International",
    "in_degree": 1,
    "out_degree": 0,
    "total_degree": 1,
    "lat": null,
    "lon": null
  },
  "Ghana": {
    "node_id": "Ghana",
    "node_type": "jurisdiction",
    "label": "Ghana",
    "region": "Global South",
    "in_degree": 3,
    "out_degree": 0,
    "total_degree": 3,
    "lat": null,
    "lon": null
  },
  "South Africa": {
    "node_id": "South Africa",
    "node_type": "jurisdiction",
    "label": "South Africa",
    "region": "Global South",
    "in_degree": 20,
    "out_degree": 5,
    "total_degree": 25,
    "lat": -30.5595,
    "lon": 22.9375
  },
  "Estonia": {
    "node_id": "Estonia",
    "node_type": "jurisdiction",
    "label": "Estonia",
    "region": "Global South",
    "in_degree": 0,
    "out_degree": 2,
    "total_degree": 2,
    "lat": null,
    "lon": null
  },
  "Switzerland (case before European Court of Human Rights)": {
    "node_id": "Switzerland (case before European Court of Human Rights)",
    "node_type": "jurisdiction",
    "label": "Switzerland (case before European Court of Human Rights)",
    "region": "International",
    "in_degree": 1,
    "out_degree": 0,
    "total_degree": 1,
    "lat": null,
    "lon": null
  },
  "Portugal": {
    "node_id": "Portugal",
    "node_type": "jurisdiction",
    "label": "Portugal",
    "region": "Global North",
    "in_degree": 6,
    "out_degree": 4,
    "total_degree": 10,
    "lat": 39.3999,
    "lon": -8.2245
  },
  "Ecuador": {
    "node_id": "Ecuador",
    "node_type": "jurisdiction",
    "label": "Ecuador",
    "region": "Global South",
    "in_degree": 12,
    "out_degree": 8,
    "total_degree": 20,
    "lat": null,
    "lon": null
  },
  "International (Inter-American System)": {
    "node_id": "International (Inter-American System)",
    "node_type": "jurisdiction",
    "label": "International (Inter-American System)",
    "region": "International",
    "in_degree": 205,
    "out_degree": 0,
    "total_degree": 205,
    "lat": null,
    "lon": null
  },
  "EFTA Court (supranational - primarily Norway, Iceland, Liechtenstein)": {
    "node_id": "EFTA Court (supranational - primarily Norway, Iceland, Liechtenstein)",
    "node_type": "jurisdiction",
    "label": "EFTA Court (supranational - primarily Norway, Iceland, Liechtenstein)",
    "region": "International",
    "in_degree": 1,
    "out_degree": 0,
    "total_degree": 1,
    "lat": null,
    "lon": null
  },
  "Turkey (case originated) / European Court of Human Rights (adjudicating court)": {
    "node_id": "Turkey (case originated) / European Court of Human Rights (adjudicating court)",
    "node_type": "jurisdiction",
    "label": "Turkey (case originated) / European Court of Human Rights (adjudicating court)",
    "region": "International",
    "in_degree": 1,
    "out_degree": 0,
    "total_degree": 1,
    "lat": null,
    "lon": null
  },
  "International - Inter-American Court of Human Rights": {
    "node_id": "International - Inter-American Court of Human Rights",
    "node_type": "jurisdiction",
    "label": "International - Inter-American Court of Human Rights",
    "region": "International",
    "in_degree": 6,
    "out_degree": 0,
    "total_degree": 6,
    "lat": null,
    "lon": null
  },
  "Indonesia": {
    "node_id": "Indonesia",
    "node_type": "jurisdiction",
    "label": "Indonesia",
    "region": "Global South",
    "in_degree": 3,
    "out_degree": 5,
    "total_degree": 8,
    "lat": -0.7893,
    "lon": 113.9213
  },
  "Sweden": {
    "node_id": "Sweden",
    "node_type": "jurisdiction",
    "label": "Sweden",
    "region": "International",
    "in_degree": 96,
    "out_degree": 0,
    "total_degree": 96,
    "lat": 60.1282,
    "lon": 18.6435
  },
  "International - Inter-American System": {
    "node_id": "International - Inter-American System",
    "node_type": "jurisdiction",
    "label": "International - Inter-American System",
    "region": "International",
    "in_degree": 44,
    "out_degree": 0,
    "total_degree": 44,
    "lat": null,
    "lon": null
  },
  "South West Africa/Namibia": {
    "node_id": "South West Africa/Namibia",
    "node_type": "jurisdiction",
    "label": "South West Africa/Namibia",
    "region": "Global South",
    "in_degree": 1,
    "out_degree": 0,
    "total_degree": 1,
    "lat": null,
    "lon": null
  },
  "European Convention on Human Rights System (Council of Europe)": {
    "node_id": "European Convention on Human Rights System (Council of Europe)",
    "node_type": "jurisdiction",
    "label": "European Convention on Human Rights System (Council of Europe)",
    "region": "International",
    "in_degree": 4,
    "out_degree": 0,
    "total_degree": 4,
    "lat": null,
    "lon": null
  },
  "Germany or Austria": {
    "node_id": "Germany or Austria",
    "node_type": "jurisdiction",
    "label": "Germany or Austria",
    "region": "Global North",
    "in_degree": 2,
    "out_degree": 0,
    "total_degree": 2,
    "lat": null,
    "lon": null
  },
  "New Zealand": {
    "node_id": "New Zealand",
    "node_type": "jurisdiction",
    "label": "New Zealand",
    "region": "Global North",
    "in_degree": 27,
    "out_degree": 212,
    "total_degree": 239,
    "lat": -40.9006,
    "lon": 174.886
  },
  "Eastern Caribbean States": {
    "node_id": "Eastern Caribbean States",
    "node_type": "jurisdiction",
    "label": "Eastern Caribbean States",
    "region": "Global South",
    "in_degree": 2,
    "out_degree": 0,
    "total_degree": 2,
    "lat": null,
    "lon": null
  },
  "United Kingdom, Canada, Australia, or New Zealand": {
    "node_id": "United Kingdom, Canada, Australia, or New Zealand",
    "node_type": "jurisdiction",
    "label": "United Kingdom, Canada, Australia, or New Zealand",
    "region": "Global North",
    "in_degree": 1,
    "out_degree": 0,
    "total_degree": 1,
    "lat": null,
    "lon": null
  },
  "England and Wales (United Kingdom)": {
    "node_id": "England and Wales (United Kingdom)",
    "node_type": "jurisdiction",
    "label": "England and Wales (United Kingdom)",
    "region": "Global North",
    "in_degree": 33,
    "out_degree": 0,
    "total_degree": 33,
    "lat": null,
    "lon": null
  },
  "European Union/European Court of Justice": {
    "node_id": "European Union/European Court of Justice",
    "node_type": "jurisdiction",
    "label": "European Union/European Court of Justice",
    "region": "International",
    "in_degree": 1,
    "out_degree": 0,
    "total_degree": 1,
    "lat": null,
    "lon": null
  },
  "Turkey": {
    "node_id": "Turkey",
    "node_type": "jurisdiction",
    "label": "Turkey",
    "region": "International",
    "in_degree": 13,
    "out_degree": 0,
    "total_degree": 13,
    "lat": null,
    "lon": null
  },
  "European Union (Germany)": {
    "node_id": "European Union (Germany)",
    "node_type": "jurisdiction",
    "label": "European Union (Germany)",
    "region": "International",
    "in_degree": 1,
    "out_degree": 0,
    "total_degree": 1,
    "lat": null,
    "lon": null
  },
  "Peru": {
    "node_id": "Peru",
    "node_type": "jurisdiction",
    "label": "Peru",
    "region": "Global South",
    "in_degree": 3,
    "out_degree": 26,
    "total_degree": 29,
    "lat": null,
    "lon": null
  },
  "International Arbitration (NAFTA)": {
    "node_id": "International Arbitration (NAFTA)",
    "node_type": "jurisdiction",
    "label": "International Arbitration (NAFTA)",
    "region": "International",
    "in_degree": 1,
    "out_degree": 0,
    "total_degree": 1,
    "lat": null,
    "lon": null
  },
  "Germany": {
    "node_id": "Germany",
    "node_type": "jurisdiction",
    "label": "Germany",
    "region": "International",
    "in_degree": 101,
    "out_degree": 18,
    "total_degree": 119,
    "lat": 51.1657,
    "lon": 10.4515
  },
  "Taiwan (Republic of China)": {
    "node_id": "Taiwan (Republic of China)",
    "node_type": "jurisdiction",
    "label": "Taiwan (Republic of China)",
    "region": "Global North",
    "in_degree": 9,
    "out_degree": 0,
    "total_degree": 9,
    "lat": null,
    "lon": null
  },
  "Kenya": {
    "node_id": "Kenya",
    "node_type": "jurisdiction",
    "label": "Kenya",
    "region": "Global South",
    "in_degree": 3,
    "out_degree": 29,
    "total_degree": 32,
    "lat": -0.0236,
    "lon": 37.9062
  },
  "France/Council of Europe": {
    "node_id": "France/Council of Europe",
    "node_type": "jurisdiction",
    "label": "France/Council of Europe",
    "region": "International",
    "in_degree": 9,
    "out_degree": 0,
    "total_degree": 9,
    "lat": null,
    "lon": null
  },
  "United Kingdom or Canada": {
    "node_id": "United Kingdom or Canada",
    "node_type": "jurisdiction",
    "label": "United Kingdom or Canada",
    "region": "Global North",
    "in_degree": 1,
    "out_degree": 0,
    "total_degree": 1,
    "lat": null,
    "lon": null
  },
  "Denmark": {
    "node_id": "Denmark",
    "node_type": "jurisdiction",
    "label": "Denmark",
    "region": "Global North",
    "in_degree": 1,
    "out_degree": 0,
    "total_degree": 1,
    "lat": 56.2639,
    "lon": 9.5018
  },
  "European Union (Court of Justice of the European Union)": {
    "node_id": "European Union (Court of Justice of the European Union)",
    "node_type": "jurisdiction",
    "label": "European Union (Court of Justice of the European Union)",
    "region": "International",
    "in_degree": 1,
    "out_degree": 0,
    "total_degree": 1,
    "lat": null,
    "lon": null
  },
  "North Macedonia": {
    "node_id": "North Macedonia",
    "node_type": "jurisdiction",
    "label": "North Macedonia",
    "region": "Global North",
    "in_degree": 1,
    "out_degree": 0,
    "total_degree": 1,
    "lat": null,
    "lon": null
  },
  "Switzerland/European Court of Human Rights": {
    "node_id": "Switzerland/European Court of Human Rights",
    "node_type": "jurisdiction",
    "label": "Switzerland/European Court of Human Rights",
    "region": "International",
    "in_degree": 2,
    "out_degree": 0,
    "total_degree": 2,
    "lat": null,
    "lon": null
  },
  "United Kingdom": {
    "node_id": "United Kingdom",
    "node_type": "jurisdiction",
    "label": "United Kingdom",
    "region": "Global North",
    "in_degree": 423,
    "out_degree": 568,
    "total_degree": 991,
    "lat": 55.3781,
    "lon": -3.436
  },
  "United Kingdom (Northern Ireland)": {
    "node_id": "United Kingdom (Northern Ireland)",
    "node_type": "jurisdiction",
    "label": "United Kingdom (Northern Ireland)",
    "region": "Global North",
    "in_degree": 18,
    "out_degree": 0,
    "total_degree": 18,
    "lat": null,
    "lon": null
  },
  "France (but decided by European Court of Human Rights)": {
    "node_id": "France (but decided by European Court of Human Rights)",
    "node_type": "jurisdiction",
    "label": "France (but decided by European Court of Human Rights)",
    "region": "International",
    "in_degree": 1,
    "out_degree": 0,
    "total_degree": 1,
    "lat": null,
    "lon": null
  },
  "Saint Kitts and Nevis": {
    "node_id": "Saint Kitts and Nevis",
    "node_type": "jurisdiction",
    "label": "Saint Kitts and Nevis",
    "region": "Global South",
    "in_degree": 1,
    "out_degree": 0,
    "total_degree": 1,
    "lat": null,
    "lon": null
  },
  "Ukraine": {
    "node_id": "Ukraine",
    "node_type": "jurisdiction",
    "label": "Ukraine",
    "region": "International",
    "in_degree": 4,
    "out_degree": 0,
    "total_degree": 4,
    "lat": null,
    "lon": null
  },
  "Poland": {
    "node_id": "Poland",
    "node_type": "jurisdiction",
    "label": "Poland",
    "region": "Global North",
    "in_degree": 3,
    "out_degree": 5,
    "total_degree": 8,
    "lat": null,
    "lon": null
  },
  "Colombia": {
    "node_id": "Colombia",
    "node_type": "jurisdiction",
    "label": "Colombia",
    "region": "Global South",
    "in_degree": 70,
    "out_degree": 34,
    "total_degree": 104,
    "lat": 4.5709,
    "lon": -74.2973
  },
  "Belize": {
    "node_id": "Belize",
    "node_type": "jurisdiction",
    "label": "Belize",
    "region": "Global South",
    "in_degree": 4,
    "out_degree": 0,
    "total_degree": 4,
    "lat": null,
    "lon": null
  },
  "European Union/United Kingdom": {
    "node_id": "European Union/United Kingdom",
    "node_type": "jurisdiction",
    "label": "European Union/United Kingdom",
    "region": "International",
    "in_degree": 1,
    "out_degree": 0,
    "total_degree": 1,
    "lat": null,
    "lon": null
  },
  "Council of Europe": {
    "node_id": "Council of Europe",
    "node_type": "jurisdiction",
    "label": "Council of Europe",
    "region": "International",
    "in_degree": 107,
    "out_degree": 0,
    "total_degree": 107,
    "lat": null,
    "lon": null
  },
  "European Union/Supranational": {
    "node_id": "European Union/Supranational",
    "node_type": "jurisdiction",
    "label": "European Union/Supranational",
    "region": "International",
    "in_degree": 1,
    "out_degree": 0,
    "total_degree": 1,
    "lat": null,
    "lon": null
  },
  "International (ICSID)": {
    "node_id": "International (ICSID)",
    "node_type": "jurisdiction",
    "label": "International (ICSID)",
    "region": "International",
    "in_degree": 5,
    "out_degree": 0,
    "total_degree": 5,
    "lat": null,
    "lon": null
  },
  "International (ICSID/Investment Arbitration)": {
    "node_id": "International (ICSID/Investment Arbitration)",
    "node_type": "jurisdiction",
    "label": "International (ICSID/Investment Arbitration)",
    "region": "International",
    "in_degree": 1,
    "out_degree": 0,
    "total_degree": 1,
    "lat": null,
    "lon": null
  },
  "United Nations": {
    "node_id": "United Nations",
    "node_type": "jurisdiction",
    "label": "United Nations",
    "region": "International",
    "in_degree": 67,
    "out_degree": 0,
    "total_degree": 67,
    "lat": null,
    "lon": null
  },
  "International/Inter-American System": {
    "node_id": "International/Inter-American System",
    "node_type": "jurisdiction",
    "label": "International/Inter-American System",
    "region": "International",
    "in_degree": 2,
    "out_degree": 0,
    "total_degree": 2,
    "lat": null,
    "lon": null
  },
  "Scotland/United Kingdom": {
    "node_id": "Scotland/United Kingdom",
    "node_type": "jurisdiction",
    "label": "Scotland/United Kingdom",
    "region": "Global North",
    "in_degree": 3,
    "out_degree": 0,
    "total_degree": 3,
    "lat": null,
    "lon": null
  },
  "Nepal": {
    "node_id": "Nepal",
    "node_type": "jurisdiction",
    "label": "Nepal",
    "region": "Global South",
    "in_degree": 5,
    "out_degree": 0,
    "total_degree": 5,
    "lat": null,
    "lon": null
  },
  "European Union/Council of Europe": {
    "node_id": "European Union/Council of Europe",
    "node_type": "jurisdiction",
    "label": "European Union/Council of Europe",
    "region": "International",
    "in_degree": 1,
    "out_degree": 0,
    "total_degree": 1,
    "lat": null,
    "lon": null
  },
  "International (NAFTA)": {
    "node_id": "International (NAFTA)",
    "node_type": "jurisdiction",
    "label": "International (NAFTA)",
    "region": "International",
    "in_degree": 1,
    "out_degree": 0,
    "total_degree": 1,
    "lat": null,
    "lon": null
  },
  "Spain": {
    "node_id": "Spain",
    "node_type": "jurisdiction",
    "label": "Spain",
    "region": "International",
    "in_degree": 143,
    "out_degree": 38,
    "total_degree": 181,
    "lat": 40.4637,
    "lon": -3.7492
  },
  "England and Wales": {
    "node_id": "England and Wales",
    "node_type": "jurisdiction",
    "label": "England and Wales",
    "region": "Global North",
    "in_degree": 321,
    "out_degree": 0,
    "total_degree": 321,
    "lat": null,
    "lon": null
  },
  "International Court of Justice": {
    "node_id": "International Court of Justice",
    "node_type": "jurisdiction",
    "label": "International Court of Justice",
    "region": "International",
    "in_degree": 44,
    "out_degree": 0,
    "total_degree": 44,
    "lat": null,
    "lon": null
  },
  "Singapore": {
    "node_id": "Singapore",
    "node_type": "jurisdiction",
    "label": "Singapore",
    "region": "Global South",
    "in_degree": 1,
    "out_degree": 0,
    "total_degree": 1,
    "lat": null,
    "lon": null
  },
  "International (NAFTA/ICSID Arbitration)": {
    "node_id": "International (NAFTA/ICSID Arbitration)",
    "node_type": "jurisdiction",
    "label": "International (NAFTA/ICSID Arbitration)",
    "region": "International",
    "in_degree": 1,
    "out_degree": 0,
    "total_degree": 1,
    "lat": null,
    "lon": null
  },
  "International/Multiple Jurisdictions": {
    "node_id": "International/Multiple Jurisdictions",
    "node_type": "jurisdiction",
    "label": "International/Multiple Jurisdictions",
    "region": "International",
    "in_degree": 2,
    "out_degree": 0,
    "total_degree": 2,
    "lat": null,
    "lon": null
  },
  "United States of America": {
    "node_id": "United States of America",
    "node_type": "jurisdiction",
    "label": "United States of America",
    "region": "Global North",
    "in_degree": 3,
    "out_degree": 0,
    "total_degree": 3,
    "lat": null,
    "lon": null
  },
  "International (Arbitration)": {
    "node_id": "International (Arbitration)",
    "node_type": "jurisdiction",
    "label": "International (Arbitration)",
    "region": "International",
    "in_degree": 10,
    "out_degree": 0,
    "total_degree": 10,
    "lat": null,
    "lon": null
  },
  "Scotland (United Kingdom)": {
    "node_id": "Scotland (United Kingdom)",
    "node_type": "jurisdiction",
    "label": "Scotland (United Kingdom)",
    "region": "Global North",
    "in_degree": 1,
    "out_degree": 0,
    "total_degree": 1,
    "lat": null,
    "lon": null
  },
  "Sierra Leone": {
    "node_id": "Sierra Leone",
    "node_type": "jurisdiction",
    "label": "Sierra Leone",
    "region": "Global South",
    "in_degree": 1,
    "out_degree": 0,
    "total_degree": 1,
    "lat": null,
    "lon": null
  },
  "Taiwan": {
    "node_id": "Taiwan",
    "node_type": "jurisdiction",
    "label": "Taiwan",
    "region": "Global South",
    "in_degree": 0,
    "out_degree": 9,
    "total_degree": 9,
    "lat": null,
    "lon": null
  },
  "International Arbitration (Sweden)": {
    "node_id": "International Arbitration (Sweden)",
    "node_type": "jurisdiction",
    "label": "International Arbitration (Sweden)",
    "region": "International",
    "in_degree": 1,
    "out_degree": 0,
    "total_degree": 1,
    "lat": null,
    "lon": null
  },
  "International (Sweden - seat of arbitration)": {
    "node_id": "International (Sweden - seat of arbitration)",
    "node_type": "jurisdiction",
    "label": "International (Sweden - seat of arbitration)",
    "region": "International",
    "in_degree": 2,
    "out_degree": 0,
    "total_degree": 2,
    "lat": null,
    "lon": null
  },
  "Unknown": {
    "node_id": "Unknown",
    "node_type": "jurisdiction",
    "label": "Unknown",
    "region": "Unknown",
    "in_degree": 287,
    "out_degree": 0,
    "total_degree": 287,
    "lat": null,
    "lon": null
  },
  "Bangladesh": {
    "node_id": "Bangladesh",
    "node_type": "jurisdiction",
    "label": "Bangladesh",
    "region": "Global South",
    "in_degree": 1,
    "out_degree": 0,
    "total_degree": 1,
    "lat": 23.685,
    "lon": 90.3563
  },
  "Australia": {
    "node_id": "Australia",
    "node_type": "jurisdiction",
    "label": "Australia",
    "region": "Global North",
    "in_degree": 86,
    "out_degree": 453,
    "total_degree": 539,
    "lat": -25.2744,
    "lon": 133.7751
  },
  "Brazil": {
    "node_id": "Brazil",
    "node_type": "jurisdiction",
    "label": "Brazil",
    "region": "Global South",
    "in_degree": 12,
    "out_degree": 136,
    "total_degree": 148,
    "lat": -14.235,
    "lon": -51.9253
  },
  "Guernsey": {
    "node_id": "Guernsey",
    "node_type": "jurisdiction",
    "label": "Guernsey",
    "region": "Global North",
    "in_degree": 1,
    "out_degree": 0,
    "total_degree": 1,
    "lat": null,
    "lon": null
  },
  "Austria": {
    "node_id": "Austria",
    "node_type": "jurisdiction",
    "label": "Austria",
    "region": "Global North",
    "in_degree": 2,
    "out_degree": 49,
    "total_degree": 51,
    "lat": 47.5162,
    "lon": 14.5501
  },
  "France (via European Court of Human Rights)": {
    "node_id": "France (via European Court of Human Rights)",
    "node_type": "jurisdiction",
    "label": "France (via European Court of Human Rights)",
    "region": "International",
    "in_degree": 1,
    "out_degree": 0,
    "total_degree": 1,
    "lat": null,
    "lon": null
  },
  "European Union (Belgium)": {
    "node_id": "European Union (Belgium)",
    "node_type": "jurisdiction",
    "label": "European Union (Belgium)",
    "region": "International",
    "in_degree": 1,
    "out_degree": 0,
    "total_degree": 1,
    "lat": null,
    "lon": null
  },
  "International - World Trade Organization": {
    "node_id": "International - World Trade Organization",
    "node_type": "jurisdiction",
    "label": "International - World Trade Organization",
    "region": "International",
    "in_degree": 32,
    "out_degree": 0,
    "total_degree": 32,
    "lat": null,
    "lon": null
  },
  "International": {
    "node_id": "International",
    "node_type": "jurisdiction",
    "label": "International",
    "region": "International",
    "in_degree": 68,
    "out_degree": 3023,
    "total_degree": 3091,
    "lat": null,
    "lon": null
  },
  "China": {
    "node_id": "China",
    "node_type": "jurisdiction",
    "label": "China",
    "region": "Global South",
    "in_degree": 1,
    "out_degree": 0,
    "total_degree": 1,
    "lat": null,
    "lon": null
  },
  "Ireland/European Union": {
    "node_id": "Ireland/European Union",
    "node_type": "jurisdiction",
    "label": "Ireland/European Union",
    "region": "International",
    "in_degree": 4,
    "out_degree": 0,
    "total_degree": 4,
    "lat": null,
    "lon": null
  },
  "Hungary": {
    "node_id": "Hungary",
    "node_type": "jurisdiction",
    "label": "Hungary",
    "region": "Global South",
    "in_degree": 14,
    "out_degree": 13,
    "total_degree": 27,
    "lat": null,
    "lon": null
  },
  "Mexico": {
    "node_id": "Mexico",
    "node_type": "jurisdiction",
    "label": "Mexico",
    "region": "Global South",
    "in_degree": 3,
    "out_degree": 18,
    "total_degree": 21,
    "lat": 23.6345,
    "lon": -102.5528
  },
  "Norway (case heard by European Court of Human Rights)": {
    "node_id": "Norway (case heard by European Court of Human Rights)",
    "node_type": "jurisdiction",
    "label": "Norway (case heard by European Court of Human Rights)",
    "region": "International",
    "in_degree": 1,
    "out_degree": 0,
    "total_degree": 1,
    "lat": null,
    "lon": null
  },
  "International (Sweden as seat)": {
    "node_id": "International (Sweden as seat)",
    "node_type": "jurisdiction",
    "label": "International (Sweden as seat)",
    "region": "International",
    "in_degree": 2,
    "out_degree": 0,
    "total_degree": 2,
    "lat": null,
    "lon": null
  },
  "International (African Commission on Human and Peoples' Rights)": {
    "node_id": "International (African Commission on Human and Peoples' Rights)",
    "node_type": "jurisdiction",
    "label": "International (African Commission on Human and Peoples' Rights)",
    "region": "International",
    "in_degree": 1,
    "out_degree": 0,
    "total_degree": 1,
    "lat": null,
    "lon": null
  },
  "International (Council of Europe)": {
    "node_id": "International (Council of Europe)",
    "node_type": "jurisdiction",
    "label": "International (Council of Europe)",
    "region": "International",
    "in_degree": 342,
    "out_degree": 0,
    "total_degree": 342,
    "lat": null,
    "lon": null
  },
  "International Tribunal": {
    "node_id": "International Tribunal",
    "node_type": "jurisdiction",
    "label": "International Tribunal",
    "region": "International",
    "in_degree": 5,
    "out_degree": 0,
    "total_degree": 5,
    "lat": 52.0866,
    "lon": 4.2955
  },
  "International Arbitration (ICSID/NAFTA)": {
    "node_id": "International Arbitration (ICSID/NAFTA)",
    "node_type": "jurisdiction",
    "label": "International Arbitration (ICSID/NAFTA)",
    "region": "International",
    "in_degree": 1,
    "out_degree": 0,
    "total_degree": 1,
    "lat": null,
    "lon": null
  },
  "Turkey (case originated) / European Court of Human Rights": {
    "node_id": "Turkey (case originated) / European Court of Human Rights",
    "node_type": "jurisdiction",
    "label": "Turkey (case originated) / European Court of Human Rights",
    "region": "International",
    "in_degree": 1,
    "out_degree": 0,
    "total_degree": 1,
    "lat": null,
    "lon": null
  },
  "Luxembourg": {
    "node_id": "Luxembourg",
    "node_type": "jurisdiction",
    "label": "Luxembourg",
    "region": "Global North",
    "in_degree": 2,
    "out_degree": 11,
    "total_degree": 13,
    "lat": null,
    "lon": null
  },
  "Cameroon": {
    "node_id": "Cameroon",
    "node_type": "jurisdiction",
    "label": "Cameroon",
    "region": "Global South",
    "in_degree": 1,
    "out_degree": 0,
    "total_degree": 1,
    "lat": null,
    "lon": null
  },
  "Zambia": {
    "node_id": "Zambia",
    "node_type": "jurisdiction",
    "label": "Zambia",
    "region": "Global South",
    "in_degree": 1,
    "out_degree": 0,
    "total_degree": 1,
    "lat": null,
    "lon": null
  },
  "Antigua and Barbuda": {
    "node_id": "Antigua and Barbuda",
    "node_type": "jurisdiction",
    "label": "Antigua and Barbuda",
    "region": "Global South",
    "in_degree": 2,
    "out_degree": 0,
    "total_degree": 2,
    "lat": null,
    "lon": null
  },
  "Benin": {
    "node_id": "Benin",
    "node_type": "jurisdiction",
    "label": "Benin",
    "region": "Global South",
    "in_degree": 1,
    "out_degree": 0,
    "total_degree": 1,
    "lat": null,
    "lon": null
  },
  "Italy": {
    "node_id": "Italy",
    "node_type": "jurisdiction",
    "label": "Italy",
    "region": "Global North",
    "in_degree": 47,
    "out_degree": 47,
    "total_degree": 94,
    "lat": 41.8719,
    "lon": 12.5674
  },
  "Romania": {
    "node_id": "Romania",
    "node_type": "jurisdiction",
    "label": "Romania",
    "region": "Global South",
    "in_degree": 0,
    "out_degree": 53,
    "total_degree": 53,
    "lat": null,
    "lon": null
  },
  "International Arbitration (Netherlands)": {
    "node_id": "International Arbitration (Netherlands)",
    "node_type": "jurisdiction",
    "label": "International Arbitration (Netherlands)",
    "region": "International",
    "in_degree": 1,
    "out_degree": 0,
    "total_degree": 1,
    "lat": null,
    "lon": null
  },
  "Uganda": {
    "node_id": "Uganda",
    "node_type": "jurisdiction",
    "label": "Uganda",
    "region": "Global South",
    "in_degree": 1,
    "out_degree": 0,
    "total_degree": 1,
    "lat": null,
    "lon": null
  },
  "Romania (case before European Court of Human Rights)": {
    "node_id": "Romania (case before European Court of Human Rights)",
    "node_type": "jurisdiction",
    "label": "Romania (case before European Court of Human Rights)",
    "region": "International",
    "in_degree": 1,
    "out_degree": 0,
    "total_degree": 1,
    "lat": null,
    "lon": null
  },
  "International/Council of Europe": {
    "node_id": "International/Council of Europe",
    "node_type": "jurisdiction",
    "label": "International/Council of Europe",
    "region": "International",
    "in_degree": 1,
    "out_degree": 0,
    "total_degree": 1,
    "lat": null,
    "lon": null
  },
  "European Union (supranational)": {
    "node_id": "European Union (supranational)",
    "node_type": "jurisdiction",
    "label": "European Union (supranational)",
    "region": "International",
    "in_degree": 1,
    "out_degree": 0,
    "total_degree": 1,
    "lat": null,
    "lon": null
  },
  "International (Iran-United States Claims Tribunal)": {
    "node_id": "International (Iran-United States Claims Tribunal)",
    "node_type": "jurisdiction",
    "label": "International (Iran-United States Claims Tribunal)",
    "region": "International",
    "in_degree": 1,
    "out_degree": 0,
    "total_degree": 1,
    "lat": null,
    "lon": null
  },
  "India": {
    "node_id": "India",
    "node_type": "jurisdiction",
    "label": "India",
    "region": "Global South",
    "in_degree": 42,
    "out_degree": 5,
    "total_degree": 47,
    "lat": 20.5937,
    "lon": 78.9629
  },
  "South Korea": {
    "node_id": "South Korea",
    "node_type": "jurisdiction",
    "label": "South Korea",
    "region": "Global North",
    "in_degree": 2,
    "out_degree": 14,
    "total_degree": 16,
    "lat": null,
    "lon": null
  },
  "Jamaica": {
    "node_id": "Jamaica",
    "node_type": "jurisdiction",
    "label": "Jamaica",
    "region": "Global South",
    "in_degree": 1,
    "out_degree": 0,
    "total_degree": 1,
    "lat": null,
    "lon": null
  },
  "Inter-American Human Rights System": {
    "node_id": "Inter-American Human Rights System",
    "node_type": "jurisdiction",
    "label": "Inter-American Human Rights System",
    "region": "International",
    "in_degree": 3,
    "out_degree": 0,
    "total_degree": 3,
    "lat": null,
    "lon": null
  },
  "France/European Court of Human Rights": {
    "node_id": "France/European Court of Human Rights",
    "node_type": "jurisdiction",
    "label": "France/European Court of Human Rights",
    "region": "International",
    "in_degree": 1,
    "out_degree": 0,
    "total_degree": 1,
    "lat": null,
    "lon": null
  },
  "Inter-American Court of Human Rights (International Tribunal)": {
    "node_id": "Inter-American Court of Human Rights (International Tribunal)",
    "node_type": "jurisdiction",
    "label": "Inter-American Court of Human Rights (International Tribunal)",
    "region": "International",
    "in_degree": 18,
    "out_degree": 0,
    "total_degree": 18,
    "lat": null,
    "lon": null
  },
  "European Patent Office": {
    "node_id": "European Patent Office",
    "node_type": "jurisdiction",
    "label": "European Patent Office",
    "region": "International",
    "in_degree": 1,
    "out_degree": 0,
    "total_degree": 1,
    "lat": null,
    "lon": null
  },
  "England": {
    "node_id": "England",
    "node_type": "jurisdiction",
    "label": "England",
    "region": "Global North",
    "in_degree": 9,
    "out_degree": 0,
    "total_degree": 9,
    "lat": null,
    "lon": null
  },
  "International Arbitration (Permanent Court of Arbitration)": {
    "node_id": "International Arbitration (Permanent Court of Arbitration)",
    "node_type": "jurisdiction",
    "label": "International Arbitration (Permanent Court of Arbitration)",
    "region": "International",
    "in_degree": 1,
    "out_degree": 0,
    "total_degree": 1,
    "lat": null,
    "lon": null
  },
  "Türkiye": {
    "node_id": "Türkiye",
    "node_type": "jurisdiction",
    "label": "Türkiye",
    "region": "Global South",
    "in_degree": 0,
    "out_degree": 6,
    "total_degree": 6,
    "lat": null,
    "lon": null
  },
  "African Union": {
    "node_id": "African Union",
    "node_type": "jurisdiction",
    "label": "African Union",
    "region": "International",
    "in_degree": 1,
    "out_degree": 0,
    "total_degree": 1,
    "lat": null,
    "lon": null
  },
  "Federated States of Micronesia": {
    "node_id": "Federated States of Micronesia",
    "node_type": "jurisdiction",
    "label": "Federated States of Micronesia",
    "region": "Global South",
    "in_degree": 1,
    "out_degree": 0,
    "total_degree": 1,
    "lat": null,
    "lon": null
  },
  "France": {
    "node_id": "France",
    "node_type": "jurisdiction",
    "label": "France",
    "region": "Global North",
    "in_degree": 64,
    "out_degree": 17,
    "total_degree": 81,
    "lat": 46.2276,
    "lon": 2.2137
  },
  "Inter-American Court of Human Rights (Regional International Court)": {
    "node_id": "Inter-American Court of Human Rights (Regional International Court)",
    "node_type": "jurisdiction",
    "label": "Inter-American Court of Human Rights (Regional International Court)",
    "region": "International",
    "in_degree": 1,
    "out_degree": 0,
    "total_degree": 1,
    "lat": null,
    "lon": null
  },
  "Council of Europe (European Court of Human Rights)": {
    "node_id": "Council of Europe (European Court of Human Rights)",
    "node_type": "jurisdiction",
    "label": "Council of Europe (European Court of Human Rights)",
    "region": "International",
    "in_degree": 1,
    "out_degree": 0,
    "total_degree": 1,
    "lat": null,
    "lon": null
  },
  "Scotland": {
    "node_id": "Scotland",
    "node_type": "jurisdiction",
    "label": "Scotland",
    "region": "Global North",
    "in_degree": 11,
    "out_degree": 0,
    "total_degree": 11,
    "lat": null,
    "lon": null
  },
  "International (World Trade Organization)": {
    "node_id": "International (World Trade Organization)",
    "node_type": "jurisdiction",
    "label": "International (World Trade Organization)",
    "region": "International",
    "in_degree": 7,
    "out_degree": 0,
    "total_degree": 7,
    "lat": null,
    "lon": null
  },
  "International (Permanent Court of Arbitration)": {
    "node_id": "International (Permanent Court of Arbitration)",
    "node_type": "jurisdiction",
    "label": "International (Permanent Court of Arbitration)",
    "region": "International",
    "in_degree": 3,
    "out_degree": 0,
    "total_degree": 3,
    "lat": null,
    "lon": null
  },
  "Organization of American States": {
    "node_id": "Organization of American States",
    "node_type": "jurisdiction",
    "label": "Organization of American States",
    "region": "International",
    "in_degree": 17,
    "out_degree": 0,
    "total_degree": 17,
    "lat": null,
    "lon": null
  },
  "Guyana": {
    "node_id": "Guyana",
    "node_type": "jurisdiction",
    "label": "Guyana",
    "region": "Global South",
    "in_degree": 3,
    "out_degree": 0,
    "total_degree": 3,
    "lat": null,
    "lon": null
  },
  "Caribbean Commonwealth jurisdiction": {
    "node_id": "Caribbean Commonwealth jurisdiction",
    "node_type": "jurisdiction",
    "label": "Caribbean Commonwealth jurisdiction",
    "region": "Global South",
    "in_degree": 1,
    "out_degree": 0,
    "total_degree": 1,
    "lat": null,
    "lon": null
  },
  "Andean Community": {
    "node_id": "Andean Community",
    "node_type": "jurisdiction",
    "label": "Andean Community",
    "region": "International",
    "in_degree": 2,
    "out_degree": 0,
    "total_degree": 2,
    "lat": null,
    "lon": null
  }
}